opendatalake/__init__.py
opendatalake/csv_loader.py
opendatalake/download_helper.py
opendatalake/simple_sequence.py
opendatalake/texture_augmentation.py
opendatalake/utils.py
opendatalake/classification/__init__.py
opendatalake/classification/cifar.py
opendatalake/classification/function_generator.py
opendatalake/classification/mnist.py
opendatalake/classification/named_folders.py
opendatalake/depth/__init__.py
opendatalake/depth/kitti_depth.py
opendatalake/detection/__init__.py
opendatalake/detection/bosch_tlr.py
opendatalake/detection/coco.py
opendatalake/detection/kitti_detection.py
opendatalake/detection/pascal_voc_3d.py
opendatalake/detection/udacity_autti.py
opendatalake/detection/udacity_crowdai.py
opendatalake/detection/utils.py
opendatalake/segmentation/__init__.py
opendatalake/unlabeled/__init__.py
opendatalake/unlabeled/image_folder.py
opendatalake-1.0.2.dist-info/LICENSE
opendatalake-1.0.2.dist-info/METADATA
opendatalake-1.0.2.dist-info/WHEEL
opendatalake-1.0.2.dist-info/top_level.txt
opendatalake-1.0.2.dist-info/RECORD
