Metadata-Version: 2.1
Name: opendatalake
Version: 1.0.2
Summary: A python wrapper library for various datasets.
Home-page: https://github.com/penguinmenac3/opendatalake
Author: Michael Fuerst
Author-email: mail@michaelfuerst.de
License: BSD
Download-URL: https://github.com/penguinmenac3/opendatalake/tarball/1.0.2
Platform: UNKNOWN
Classifier: Development Status :: 3 - Alpha
Classifier: Intended Audience :: Developers
Classifier: Programming Language :: Python
Requires-Dist: numpy
Requires-Dist: scikit-image
Requires-Dist: scikit-learn
Requires-Dist: scipy
Requires-Dist: matplotlib
Requires-Dist: h5py
Requires-Dist: pandas
Requires-Dist: hyperparams
